uk_gov_dash_components/Accordion.py
uk_gov_dash_components/AdditionalDetails.py
uk_gov_dash_components/AutoComplete.py
uk_gov_dash_components/ChangeLogBanner.py
uk_gov_dash_components/CheckboxList.py
uk_gov_dash_components/ComboBox.py
uk_gov_dash_components/ComponentTemplate.py
uk_gov_dash_components/CookieBanner.py
uk_gov_dash_components/CookiesPage.py
uk_gov_dash_components/Dropdown.py
uk_gov_dash_components/ExpandableMenuItem.py
uk_gov_dash_components/ListBox.py
uk_gov_dash_components/Popover.py
uk_gov_dash_components/Radios.py
uk_gov_dash_components/Tabs.py
uk_gov_dash_components/__init__.py
uk_gov_dash_components/_imports_.py
uk_gov_dash_components/dropdownArrowDown.py
uk_gov_dash_components/metadata.json
uk_gov_dash_components/package-info.json
uk_gov_dash_components/status.py
uk_gov_dash_components/uk_gov_dash_components.min.js
uk_gov_dash_components/uk_gov_dash_components.min.js.map
uk_gov_dash_components-2.1.0.dist-info/licenses/LICENSE
uk_gov_dash_components-2.1.0.dist-info/METADATA
uk_gov_dash_components-2.1.0.dist-info/WHEEL
uk_gov_dash_components-2.1.0.dist-info/top_level.txt
uk_gov_dash_components-2.1.0.dist-info/RECORD
