Metadata-Version: 2.4
Name: uk_gov_dash_components
Version: 2.1.0
Summary: Dash components for Gov UK
Author: DLUHC GovUk <pythonvisualisations@levellingup.gov.uk>
License: MIT
Classifier: Framework :: Dash
License-File: LICENSE
Dynamic: author
Dynamic: classifier
Dynamic: description
Dynamic: description-content-type
Dynamic: license
Dynamic: license-file
Dynamic: summary
